index_generator/__init__.py
index_generator/__main__.py
index_generator/icons/papirus/default.svg
index_generator/icons/papirus/application/pgp-signature.svg
index_generator/icons/papirus/application/x-tar.svg
index_generator/icons/papirus/inode/directory.svg
index_generator/models/__init__.py
index_generator/models/entries.py
index_generator/models/exceptions.py
index_generator/templates/default/index.html
index_generator/templates/default/layout.html
index_generator/templates/default-dark/index.html
index_generator/templates/default-dark/layout.html
index_generator/templates/h5ai-like/index.html
index_generator/templates/h5ai-like/script.js
index_generator/templates/h5ai-like/style.css
index_generator-0.3.0.dist-info/LICENSE
index_generator-0.3.0.dist-info/METADATA
index_generator-0.3.0.dist-info/WHEEL
index_generator-0.3.0.dist-info/entry_points.txt
index_generator-0.3.0.dist-info/top_level.txt
index_generator-0.3.0.dist-info/RECORD
