Metadata-Version: 2.1
Name: index-generator
Version: 0.3.0
Summary: Yet another index generator.
Home-page: https://github.com/index-generator-project/index-generator
Author: Index Generator Project
Author-email: 
License: MIT
Keywords: index,listing,directory
Platform: UNKNOWN
Requires-Python: >=3.5
Requires-Dist: Jinja2
